h3a/__init__.py
h3a/cli.py
h3a/config.py
h3a/context.py
h3a/execute.py
h3a/plan.py
h3a/py.typed
h3a-0.2.0.dist-info/METADATA
h3a-0.2.0.dist-info/WHEEL
h3a-0.2.0.dist-info/entry_points.txt
h3a-0.2.0.dist-info/RECORD
