Metadata-Version: 2.4
Name: h3a
Version: 0.2.0
Summary: A simple script for file archiving.
Project-URL: homepage, https://github.com/huang2002/h3a
Author-email: hhh <huanghaihua2002@qq.com>
License: ISC
Requires-Python: >=3.12
Requires-Dist: click>=8.1.8
Requires-Dist: strictyaml>=1.7.3
